uspto_odp/__init__.py
uspto_odp/controller/__init__.py
uspto_odp/controller/uspto_odp_client.py
uspto_odp/models/__init__.py
uspto_odp/models/bulk_datasets.py
uspto_odp/models/foreign_priority.py
uspto_odp/models/patent_adjustment.py
uspto_odp/models/patent_appeals_decisions.py
uspto_odp/models/patent_assignment.py
uspto_odp/models/patent_associated_documents.py
uspto_odp/models/patent_attorney.py
uspto_odp/models/patent_continuity.py
uspto_odp/models/patent_documents.py
uspto_odp/models/patent_file_wrapper.py
uspto_odp/models/patent_interferences_decisions.py
uspto_odp/models/patent_metadata.py
uspto_odp/models/patent_petition_decision.py
uspto_odp/models/patent_search_download.py
uspto_odp/models/patent_status.py
uspto_odp/models/patent_status_codes.py
uspto_odp/models/patent_transactions.py
uspto_odp/models/patent_trials_decisions.py
uspto_odp/models/patent_trials_documents.py
uspto_odp/models/patent_trials_proceedings.py
uspto_odp/models/search_result.py
uspto_odp-1.0.1.dist-info/licenses/LICENSE
uspto_odp-1.0.1.dist-info/METADATA
uspto_odp-1.0.1.dist-info/WHEEL
uspto_odp-1.0.1.dist-info/top_level.txt
uspto_odp-1.0.1.dist-info/RECORD
