Metadata-Version: 2.4
Name: uspto_odp
Version: 1.0.1
Summary: USPTO Open Data Portal Client
Author-email: Ken Thompson <kenthompson1@gmail.com>
Project-URL: Homepage, https://github.com/KennethThompson/uspto_odp
Project-URL: Documentation, https://kenneththompson.github.io/uspto_odp/
Project-URL: Issues, https://github.com/KennethThompson/uspto_odp/issues
Classifier: Programming Language :: Python :: 3
Classifier: License :: OSI Approved :: MIT License
Classifier: Operating System :: OS Independent
Requires-Python: >=3.9
License-File: LICENSE
Requires-Dist: aiohttp>=3.11.7
Requires-Dist: strenum>=0.4.10
Provides-Extra: dev
Requires-Dist: pytest>=7.0; extra == "dev"
Requires-Dist: pytest-asyncio; extra == "dev"
Requires-Dist: coverage; extra == "dev"
Requires-Dist: python-dotenv; extra == "dev"
Provides-Extra: docs
Requires-Dist: mkdocs>=1.5.0; extra == "docs"
Requires-Dist: mkdocs-material>=9.0.0; extra == "docs"
Requires-Dist: mkdocstrings[python]>=0.23.0; extra == "docs"
Dynamic: license-file
